grafanalib/__init__.py
grafanalib/_gen.py
grafanalib/azuredataexplorer.py
grafanalib/azuremonitor.py
grafanalib/cloudwatch.py
grafanalib/core.py
grafanalib/elasticsearch.py
grafanalib/formatunits.py
grafanalib/humio.py
grafanalib/influxdb.py
grafanalib/opentsdb.py
grafanalib/prometheus.py
grafanalib/validators.py
grafanalib/weave.py
grafanalib/zabbix.py
grafanalib-0.7.1.dist-info/LICENSE
grafanalib-0.7.1.dist-info/METADATA
grafanalib-0.7.1.dist-info/WHEEL
grafanalib-0.7.1.dist-info/entry_points.txt
grafanalib-0.7.1.dist-info/top_level.txt
grafanalib-0.7.1.dist-info/RECORD
