Metadata-Version: 2.1
Name: grafanalib
Version: 0.7.1
Summary: Library for building Grafana dashboards
Home-page: https://github.com/weaveworks/grafanalib
Author: Weaveworks
Author-email: help+grafanalib@weave.works
License: Apache
Project-URL: Documentation, https://grafanalib.readthedocs.io
Project-URL: Source, https://github.com/weaveworks/grafanalib
Classifier: Development Status :: 3 - Alpha
Classifier: Environment :: Console
Classifier: Intended Audience :: Developers
Classifier: Intended Audience :: System Administrators
Classifier: License :: OSI Approved :: Apache Software License
Classifier: Programming Language :: Python :: 3.7
Classifier: Programming Language :: Python :: 3.8
Classifier: Programming Language :: Python :: 3.9
Classifier: Programming Language :: Python :: 3.10
Classifier: Programming Language :: Python :: 3.11
Classifier: Topic :: System :: Monitoring
Provides-Extra: dev
License-File: LICENSE
